Products/PDBDebugMode/__init__.py
Products/PDBDebugMode/archetypes.py
Products/PDBDebugMode/browser.py
Products/PDBDebugMode/cmfplone.py
Products/PDBDebugMode/configure.zcml
Products/PDBDebugMode/debugger.py
Products/PDBDebugMode/errorlog.py
Products/PDBDebugMode/meta.zcml
Products/PDBDebugMode/pdblogging.py
Products/PDBDebugMode/refresh.txt
Products/PDBDebugMode/runcall.py
Products/PDBDebugMode/wsgi_runcall.py
Products/PDBDebugMode/zcatalog.py
Products/PDBDebugMode/zodb.py
Products/PDBDebugMode/zodb.zcml
Products/PDBDebugMode/scripts/broken_by_class.py
Products/PDBDebugMode/scripts/broken_delete.py
products_pdbdebugmode-3.0.0.dist-info/METADATA
products_pdbdebugmode-3.0.0.dist-info/WHEEL
products_pdbdebugmode-3.0.0.dist-info/entry_points.txt
products_pdbdebugmode-3.0.0.dist-info/top_level.txt
products_pdbdebugmode-3.0.0.dist-info/RECORD
