Metadata-Version: 2.4
Name: Products.PDBDebugMode
Version: 3.0.0
Summary: Post-mortem debugging on Zope exceptions
Home-page: https://github.com/collective/Products.PDBDebugMode
Author: Ross Patterson
Author-email: me@rpatterson.net
License: GPL
Keywords: Plone,debug,pdb
Classifier: Development Status :: 5 - Production/Stable
Classifier: Environment :: Web Environment
Classifier: Topic :: Software Development :: Libraries :: Python Modules
Classifier: Framework :: Plone
Classifier: Framework :: Plone :: 6.2
Classifier: Framework :: Zope :: 4
Classifier: License :: OSI Approved :: GNU General Public License v2 (GPLv2)
Classifier: Operating System :: OS Independent
Classifier: Programming Language :: Python
Classifier: Programming Language :: Python :: 3.10
Classifier: Programming Language :: Python :: 3.11
Classifier: Programming Language :: Python :: 3.12
Classifier: Programming Language :: Python :: 3.13
Requires-Python: >=3.10
Requires-Dist: collective.monkeypatcher
Requires-Dist: Products.CMFCore
Requires-Dist: Products.CMFPlone
Requires-Dist: Zope
Provides-Extra: ipdb
Requires-Dist: ipdb>=0.3; extra == "ipdb"
Provides-Extra: zodb
Requires-Dist: zope.testrunner>=6.4; extra == "zodb"
Provides-Extra: zodb-testing
Requires-Dist: zope.testing; extra == "zodb-testing"
Dynamic: author
Dynamic: author-email
Dynamic: classifier
Dynamic: description
Dynamic: description-content-type
Dynamic: home-page
Dynamic: keywords
Dynamic: license
Dynamic: provides-extra
Dynamic: requires-dist
Dynamic: requires-python
Dynamic: summary
